Workbook

Sheet Cleaned Data
A1: ORDER ID | B1: DATE | C1: PRODUCT | D1: CATEGORY | E1: REGION | F1: QUANTITY | G1: COST PRICE | H1: SALES PRICE | I1: PROFIT | J1: TOTAL REVENUE | K1: TOTAL COST | L1: TOTAL PROFIT
A2: {=_xlfn.SEQUENCE(60)} -> 1 | B2: 46266 | C2: LAPTOP | D2: ELECTRONICS | E2: EAST | F2: 5 | G2: 44000 | H2: 52000 | I2: =(H2-G2 ) -> 8000 | J2: =F2*H2 -> 260000 | K2: =F2*G2 -> 220000 | L2: =F2*I2 -> 40000
A3: 2 | B3: 46267 | C3: KEYBOARD | D3: ELECTRONICS | E3: WEST | F3: 7 | G3: 1500 | H3: 2200 | I3: =(H3-G3 ) -> 700 | J3: =F3*H3 -> 15400 | K3: =F3*G3 -> 10500 | L3: =F3*I3 -> 4900
A4: 3 | B4: 46268 | C4: MOUSE | D4: ELECTRONICS | E4: WEST | F4: 12 | G4: 1200 | H4: 2000 | I4: =(H4-G4 ) -> 800 | J4: =F4*H4 -> 24000 | K4: =F4*G4 -> 14400 | L4: =F4*I4 -> 9600
A5: 4 | B5: 46269 | C5: BED | D5: FURNITURE | E5: NORTH | F5: 8 | G5: 20000 | H5: 25000 | I5: =(H5-G5 ) -> 5000 | J5: =F5*H5 -> 200000 | K5: =F5*G5 -> 160000 | L5: =F5*I5 -> 40000
A6: 5 | B6: 46270 | C6: SOFA | D6: FURNITURE | E6: SOUTH | F6: 15 | G6: 25000 | H6: 30000 | I6: =(H6-G6 ) -> 5000 | J6: =F6*H6 -> 450000 | K6: =F6*G6 -> 375000 | L6: =F6*I6 -> 75000
A7: 6 | B7: 46271 | C7: OFFICE CHAIR | D7: FURNITURE | E7: NORTH | F7: 3 | G7: 3000 | H7: 3800 | I7: =(H7-G7 ) -> 800 | J7: =F7*H7 -> 11400 | K7: =F7*G7 -> 9000 | L7: =F7*I7 -> 2400
A8: 7 | B8: 46272 | C8: POWER BANK | D8: ACCESSORIES | E8: EAST | F8: 7 | G8: 1800 | H8: 2500 | I8: =(H8-G8 ) -> 700 | J8: =F8*H8 -> 17500 | K8: =F8*G8 -> 12600 | L8: =F8*I8 -> 4900
A9: 8 | B9: 46273 | C9: PENDRIVE | D9: ACCESSORIES | E9: EAST | F9: 9 | G9: 1500 | H9: 2300 | I9: =(H9-G9 ) -> 800 | J9: =F9*H9 -> 20700 | K9: =F9*G9 -> 13500 | L9: =F9*I9 -> 7200
A10: 9 | B10: 46274 | C10: LAPTOP CHARGER | D10: ACCESSORIES | E10: SOUTH | F10: 5 | G10: 1200 | H10: 2000 | I10: =(H10-G10 ) -> 800 | J10: =F10*H10 -> 10000 | K10: =F10*G10 -> 6000 | L10: =F10*I10 -> 4000
A11: 10 | B11: 46275 | C11: PRINTER | D11: ELECTRONICS | E11: NORTH | F11: 14 | G11: 25000 | H11: 35000 | I11: =(H11-G11 ) -> 10000 | J11: =F11*H11 -> 490000 | K11: =F11*G11 -> 350000 | L11: =F11*I11 -> 140000
A12: 11 | B12: 46276 | C12: SCANNER | D12: ELECTRONICS | E12: EAST | F12: 6 | G12: 28000 | H12: 35000 | I12: =(H12-G12 ) -> 7000 | J12: =F12*H12 -> 210000 | K12: =F12*G12 -> 168000 | L12: =F12*I12 -> 42000
A13: 12 | B13: 46277 | C13: OFFICE TABLE | D13: FURNITURE | E13: WEST | F13: 12 | G13: 4800 | H13: 5500 | I13: =(H13-G13 ) -> 700 | J13: =F13*H13 -> 66000 | K13: =F13*G13 -> 57600 | L13: =F13*I13 -> 8400
A14: 13 | B14: 46278 | C14: BOOKSHELF | D14: FURNITURE | E14: SOUTH | F14: 18 | G14: 1200 | H14: 1800 | I14: =(H14-G14 ) -> 600 | J14: =F14*H14 -> 32400 | K14: =F14*G14 -> 21600 | L14: =F14*I14 -> 10800
... A61: 60 | B61: 46325 | C61: HEADPHONES | D61: ELECTRONICS | E61: SOUTH | F61: 15 | G61: 23000 | H61: 25000 | I61: =(H61-G61 ) -> 2000 | J61: =F61*H61 -> 375000 | K61: =F61*G61 -> 345000 | L61: =F61*I61 -> 30000
H1048576: =SUM(H2:H1048575) -> 1083550

Sheet Dashboard
D4: TOTAL REVENUE | G4: TOTAL COST | J4: TOTAL PROFIT
D5: =SUM('Cleaned Data'!J2:J61) -> 10432900 | G5: =SUM('Cleaned Data'!K2:K61) -> 6336450 | J5: =SUM('Cleaned Data'!L2:L61) -> 4096450
D8: TOTAL ORDERS | G8: TOTAL QUANTITY SOLD | J8: OVERALL PROFIT MARGIN
D9: =COUNT('Cleaned Data'!A2:A61) -> 60 | G9: =SUM('Cleaned Data'!F2:F61) -> 561 | J9: =J5/D5 -> 0.3926473

Sheet  Analysis and Pivots
A1: Row Labels | B1: Sum of TOTAL REVENUE | C1: Sum of TOTAL PROFIT | E1: Row Labels | F1: Sum of TOTAL REVENUE | I1: Row Labels | J1: Sum of TOTAL REVENUE | K1: Sum of TOTAL PROFIT
A2: ACCESSORIES | B2: 630700 | C2: 116250 | E2: EAST | F2: 1608900 | I2: Sep | J2: 4533700 | K2: 857000
A3: ELECTRONICS | B3: 7844200 | C3: 3559900 | E3: NORTH | F3: 1566400 | I3: Oct | J3: 5899200 | K3: 3239450
A4: FURNITURE | B4: 1958000 | C4: 420300 | E4: NORTH | F4: 490000 | I4: Grand Total | J4: 10432900 | K4: 4096450
A5: Grand Total | B5: 10432900 | C5: 4096450 | E5: SOUTH | F5: 1968000
E6: WEST | F6: 4799600
E7: Grand Total | F7: 10432900
